unip/__init__.py
unip/api.py
unip/version.py
unip/core/__init__.py
unip/core/algorithm.py
unip/core/group.py
unip/core/node.py
unip/core/pruner.py
unip/core/score.py
unip/utils/__init__.py
unip/utils/data_type.py
unip/utils/deploy.py
unip/utils/energy.py
unip/utils/evaluation.py
unip/utils/prune_ops.py
unip/utils/saver.py
unip/utils/validate.py
Unified_Pruning-1.0.5.dist-info/LICENSE
Unified_Pruning-1.0.5.dist-info/METADATA
Unified_Pruning-1.0.5.dist-info/WHEEL
Unified_Pruning-1.0.5.dist-info/top_level.txt
Unified_Pruning-1.0.5.dist-info/RECORD
