Metadata-Version: 2.1
Name: Unified-Pruning
Version: 1.0.5
Summary: A unified framework for Pruning in Pytorch
Home-page: https://github.com/Nobreakfast/UniP
Author: Haocheng Zhao
Author-email: Haocheng.Zhao@hotmail.com
Classifier: Programming Language :: Python :: 3
Classifier: License :: OSI Approved :: MIT License
Classifier: Operating System :: OS Independent
Requires-Python: >=3.6
License-File: LICENSE
Requires-Dist: torch
Requires-Dist: torchvision
Requires-Dist: numpy
Requires-Dist: thop
Requires-Dist: tqdm
